multiple_docking/__init__.py
multiple_docking/docking.py
multiple_docking-0.15.dist-info/METADATA
multiple_docking-0.15.dist-info/WHEEL
multiple_docking-0.15.dist-info/top_level.txt
multiple_docking-0.15.dist-info/RECORD
