Metadata-Version: 2.1
Name: multiple-docking
Version: 0.15
Summary: single docking and multiple docking using a python code
Home-page: https://github.com/TharinduLab/Multiple_Docking.git
Author: Jayamal
Author-email: jayamal@sci.sjp.ac.lk
Requires-Dist: pip
Requires-Dist: openbabel
Requires-Dist: pandas
